[
  {
    "word": "ცვლადი",
    "explain": "ინახავს მონაცემთა მნიშვნელობებს."
  },
  {
    "სიტყვა": "ფუნქცია",
    "explain": "კონკრეტული დავალების შესრულება."
  },
  {
    "word": "მასივი",
    "explain": "სიის მსგავსი ობიექტი."
  },
  {
    "სიტყვა": "ობიექტი",
    "explain": "ინახავს გასაღების კოლექციებს."
  },
  {
    "სიტყვა": "მარყუჟი",
    "explain": "იმეორებს მოქმედებებს."
  },
  {
    "სიტყვა": "მდგომარეობა",
    "explain": "ამოწმებს კრიტერიუმებს."
  },
  {
    "სიტყვა": "დარეკვა",
    "explain": "ფუნქცია, როგორც არგუმენტი."
  },
  {
    "სიტყვა": "დაპირება",
    "explain": "ასახავს მომავალ შედეგს."
  },
  {
    "word": "ასინქრონიზაცია/მოლოდინი",
    "explain": "ასინქრონული კოდისთვის."
  },
  {
    "სიტყვა": "კლასი",
    "explain": "ობიექტების გეგმა."
  },
  {
    "word": "კონსოლი",
    "explain": "აწვდის გამართვის კონსოლს."
  },
  {
    "სიტყვა": "DOM",
    "explain": "წარმოადგენს HTML დოკუმენტებს."
  },
  {
    "სიტყვა": "მოვლენა",
    "explain": "პასუხი ქმედებებზე."
  },
  {
    "word": "JSON",
    "explain": "მონაცემთა გაცვლის ფორმატი."
  },
  {
    "სიტყვა": "NaN",
    "explain": "არა რიცხვი მნიშვნელობა."
  },
  {
    "სიტყვა": "ნული",
    "განმარტეთ": "არაფერს არ წარმოადგენს."
  },
  {
    "სიტყვა": "გაურკვეველი",
    "explain": "ცვლადი არ არის მინიჭებული."
  },
  {
    "სიტყვა": "ფარგლები",
    "explain": "ცვლადი წვდომის კონტექსტი."
  },
  {
    "სიტყვა": "აწევა",
    "explain": "ცვლადი/მეთოდის მოძრაობა."
  },
  {
    "სიტყვა": "დახურვა",
    "explain": "ფუნქცია შენახული მონაცემებით."
  },
  {
    "სიტყვა": "IIFE",
    "explain": "დაუყოვნებლივ გამოძახებული ფუნქციის გამოხატულება."
  },
  {
    "სიტყვა": "ნება",
    "explain": "Block Scoped ცვლადი."
  },
  {
    "სიტყვა": "კონსტ",
    "explain": "ბლოკის დიაპაზონი, უცვლელი ცვლადი."
  },
  {
    "სიტყვა": "პროტოტიპი",
    "explain": "ობიექტის პროტოტიპის თვისება."
  },
  {
    "სიტყვა": "ეს",
    "explain": "კონტექსტური მითითების საკვანძო სიტყვა."
  },
  {
    "სიტყვა": "ახალი",
    "explain": "ქმნის ახალ ობიექტს."
  },
  {
    "word": "წაშლა",
    "explain": "შლის ობიექტის თვისებას."
  },
  {
    "სიტყვა": "ტიპი",
    "explain": "აბრუნებს მონაცემთა ტიპს."
  },
  {
    "სიტყვა": "მაგალითი",
    "explain": "ამოწმებს ობიექტის მაგალითს."
  },
  {
    "word": "სცადე...დაჭერა",
    "explain": "ამუშავებს გამონაკლისებს."
  },
  {
    "სიტყვა": "საბოლოოდ",
    "explain": "ახორციელებს მცდელობის/დაჭერის შემდეგ."
  },
  {
    "სიტყვა": "გადააგდე",
    "explain": "ისვრის გამონაკლისს."
  },
  {
    "სიტყვა": "შესვენება",
    "explain": "გადის მარყუჟიდან ან გადართვით."
  },
  {
    "word": "გაგრძელება",
    "explain": "გამოტოვებს ციკლის გამეორებას."
  },
  {
    "word": "გამმართველი",
    "explain": "აჩერებს შესრულებას გამართვისთვის."
  },
  {
    "word": "მკაცრი რეჟიმი",
    "explain": "ახორციელებს უფრო მკაცრ ანალიზს."
  },
  {
    "სიტყვა": "ფანჯარა",
    "explain": "გლობალური ობიექტი ბრაუზერებში."
  },
  {
    "სიტყვა": "დოკუმენტი",
    "explain": "წვდომა და შეცვალე DOM."
  },
  {
    "სიტყვა": "ნავიგატორი",
    "explain": "ასახავს მომხმარებლის ბრაუზერს."
  },
  {
    "სიტყვა": "ეკრანი",
    "explain": "ინფორმაცია მომხმარებლის ეკრანის შესახებ."
  },
  {
    "სიტყვა": "ისტორია",
    "explain": "ბრაუზერის ნავიგაციის ისტორია."
  },
  {
    "word": "cookies",
    "explain": "მონაცემების ადგილობრივად შენახვა."
  },
  {
    "word": "SessionStorage",
    "explain": "ინახავს მონაცემებს თითო სესიაზე."
  },
  {
    "word": "LocalStorage",
    "explain": "ინახავს მონაცემებს ადგილობრივად."
  },
  {
    "სიტყვა": "მოტანა",
    "explain": "აკეთებს ქსელის მოთხოვნებს."
  },
  {
    "word": "XMLHttpRequest",
    "explain": "აკეთებს HTTP მოთხოვნებს."
  },
  {
    "სიტყვა": "AJAX",
    "explain": "ასინქრონული JavaScript და XML."
  },
  {
    "word": "SetTimeout",
    "explain": "ახორციელებს დაყოვნების შემდეგ."
  },
  {
    "word": "SetInterval",
    "explain": "განმეორებით იძახებს ფუნქციას."
  },
  {
    "word": "ClearTimeout",
    "explain": "ასუფთავებს ვადას."
  },
  {
    "word": "ClearInterval",
    "explain": "ასუფთავებს ინტერვალს."
  },
  {
    "word": "Event Loop",
    "explain": "ამუშავებს ასინქრონულ გამოძახებებს."
  },
  {
    "word": "დარეკვის რიგი",
    "explain": "რიგი გამოძახებისთვის."
  },
  {
    "word": "ვებ API",
    "explain": "ბრაუზერის მიერ მოწოდებული API."
  },
  {
    "word": "Node.js",
    "explain": "JavaScript გაშვების გარემო."
  },
  {
    "სიტყვა": "NPM",
    "explain": "Node Package Manager."
  },
  {
    "სიტყვა": "ნართი",
    "explain": "NPM-ის ალტერნატივა."
  },
  {
    "word": "ვებპაკეტი",
    "explain": "მოდულის ნაკრები."
  },
  {
    "სიტყვა": "ბაბელი",
    "explain": "JavaScript შემდგენელი."
  },
  {
    "სიტყვა": "ES6",
    "explain": "ECMAScript 2015."
  },
  {
    "word": "თარგი ლიტერალები",
    "explain": "სტრიქონის ინტერპოლაცია."
  },
  {
    "სიტყვა": "განადგურება",
    "explain": "მნიშვნელობების ამოხსნა მასივიდან ან ობიექტებიდან."
  },
  {
    "word": "Spread Operator",
    "explain": "აფართოებს iterable ელემენტებს."
  },
  {
    "word": "დასვენების პარამეტრები",
    "explain": "ასახავს არგუმენტების განუსაზღვრელ რაოდენობას."
  },
  {
    "word": "ისრის ფუნქცია",
    "explain": "მოკლე ფუნქციის სინტაქსი."
  },
  {
    "word": "ნაგულისხმევი პარამეტრები",
    "explain": "ფუნქციის პარამეტრების ნაგულისხმევი მნიშვნელობები."
  },
  {
    "word": "რუკა",
    "explain": "გასაღები-მნიშვნელობის წყვილების კოლექცია."
  },
  {
    "word": "Set",
    "explain": "უნიკალური ფასეულობების კოლექცია."
  },
  {
    "სიტყვა": "სიმბოლო",
    "explain": "ასახავს უნიკალურ იდენტიფიკატორს."
  },
  {
    "სიტყვა": "იტერატორი",
    "explain": "ობიექტი, რომელიც გამეორების საშუალებას იძლევა."
  },
  {
    "სიტყვა": "გენერატორი",
    "explain": "წარმოქმნის მნიშვნელობების თანმიმდევრობას."
  },
  {
    "სიტყვა": "მოდული",
    "explain": "განმეორებით გამოყენებადი კოდის ნაწილი."
  },
  {
    "word": "იმპორტი",
    "explain": "მოიცავს მოდულებს."
  },
  {
    "სიტყვა": "ექსპორტი",
    "explain": "მოდულების ექსპორტი."
  },
  {
    "word": "ასინქრონული ფუნქცია",
    "explain": "ამუშავებს ასინქრონულ ოპერაციებს."
  },
  {
    "სიტყვა": "ველოდები",
    "explain": "ელოდება ასინქრონიზაციის ოპერაციას."
  },
  {
    "სიტყვა": "დარეკვა ჯოჯოხეთი",
    "explain": "ჩამოკიდებული გამოძახების პრობლემა."
  },
  {
    "სიტყვა": "დაპირება",
    "explain": "აკონვერტირებს გამოძახებას დაპირებად."
  },
  {
    "სიტყვა": "ტრანსპილერი",
    "explain": "აკონვერტირებს წყაროს კოდს."
  },
  {
    "word": "პოლიშევსება",
    "explain": "ახორციელებს ფუნქციებს ძველ ბრაუზერებში."
  },
  {
    "სიტყვა": "ჭეშმარიტება",
    "explain": "მნიშვნელობები, რომლებიც ჭეშმარიტია ლოგიკურ კონტექსტში."
  },
  {
    "სიტყვა": "ყალბი",
    "explain": "მნიშვნელობები, რომლებიც ყალბია ლოგიკურ კონტექსტში."
  },
  {
    "word": "აღსრულების კონტექსტი",
    "explain": "გარემო JavaScript კოდის შესრულებისთვის."
  },
  {
    "სიტყვა": "ლექსიკური გარემო",
    "explain": "კოდის ფარგლების იერარქია."
  },
  {
    "word": "ლექსიკური სფერო",
    "explain": "ფარგლები დაფუძნებულია წყაროს კოდზე."
  },
  {
    "word": "გლობალური მასშტაბი",
    "explain": "ცვლადები ხელმისაწვდომია ყველგან."
  },
  {
    "word": "ადგილობრივი ფარგლები",
    "explain": "ცვლადები ხელმისაწვდომი კონკრეტულ ტერიტორიაზე."
  },
  {
    "word": "დაბლოკვის ფარგლები",
    "explain": "ცვლადები ბლოკების ფარგლებში."
  },
  {
    "word": "Scope Chain",
    "explain": "ფარგლების იერარქია"
  },
  {
    "word": "ფუნქციური პროგრამირება",
    "explain": "პროგრამირება ფუნქციებით."
  },
  {
    "word": "ობიექტზე ორიენტირებული პროგრამირება",
    "explain": "პროგრამირება ობიექტებით."
  },
  {
    "სიტყვა": "უცვლელი",
    "განმარტეთ": "შექმნის შემდეგ შეუცვლელია"
  },
  {
    "სიტყვა": "ცვალებადი",
    "explain": "შესაცვლელია შექმნის შემდეგ."
  },
  {
    "word": "გვერდითი ეფექტი",
    "explain": "ფუნქცია გავლენას ახდენს გარე მდგომარეობაზე."
  },
  {
    "სიტყვა": "სუფთა ფუნქცია",
    "განმარტეთ": "გვერდითი მოვლენები არ არის."
  },
  {
    "word": "უმაღლესი რიგის ფუნქცია",
    "explain": "ფუნქცია, რომელიც იღებს/აბრუნებს ფუნქციებს."
  },
  {
    "word": "პირველი კლასის ფუნქცია",
    "explain": "ფუნქცია განიხილება როგორც მნიშვნელობა."
  },
  {
    "სიტყვა": "მოხრა",
    "explain": "ფუნქციის კონვერტაცია მრავალი არგუმენტით ფუნქციების თანმიმდევრობით."
  },
  {
    "word": "ნაწილობრივი განაცხადი",
    "explain": "ფუნქციის არგუმენტების წინასწარ შევსება."
  },
  {
    "სიტყვა": "დამახსოვრება",
    "explain": "ფუნქციის ქეშირების შედეგები."
  },
  {
    "სიტყვა": "რეკურსია",
    "explain": "ფუნქცია თავის თავს იძახებს."
  },
  {
    "word": "კუდის ზარის ოპტიმიზაცია",
    "explain": "აუმჯობესებს რეკურსიულ ზარებს."
  },
  {
    "word": "მოვლენის ბუშტუკები",
    "explain": "მოვლენა ვრცელდება DOM-ზე."
  },
  {
    "word": "მოვლენის აღბეჭდვა",
    "explain": "მოვლენა ვრცელდება DOM-ში."
  },
  {
    "word": "ღონისძიების დელეგაცია",
    "explain": "მოვლენის მართვა უფრო მაღალ დონეზე."
  },
  {
    "word": "ღონისძიების მართვა",
    "explain": "მომხმარებლის მოვლენების მართვა."
  },
  {
    "word": "ღონისძიების მსმენელი",
    "explain": "უსმენს მოვლენებს."
  },
  {
    "word": "მოვლენის ობიექტი",
    "explain": "ინფორმაცია მოვლენის შესახებ."
  },
  {
    "სიტყვა": "გავრცელება",
    "explain": "ღონისძიების მოგზაურობა DOM-ის მეშვეობით."
  },
  {
    "word": "ნაგულისხმევის თავიდან აცილება",
    "explain": "აჩერებს ნაგულისხმევ მოქმედებას."
  },
  {
    "word": "შეაჩერე გავრცელება",
    "explain": "აჩერებს მოვლენის ბუშტუკებს/ჩაღებას."
  },
  {
    "სიტყვა": "სამიზნე",
    "explain": "ელემენტი, რომელმაც გამოიწვია მოვლენა."
  },
  {
    "word": "მიმდინარე სამიზნე",
    "explain": "ელემენტი მსმენელთან."
  },
  {
    "word": "AddEventListener",
    "explain": "რეგისტრირდება მოვლენის მსმენელი."
  },
  {
    "word": "RemoveEventListener",
    "explain": "აუქმებს ღონისძიების მსმენელის რეგისტრაციას."
  },
  {
    "word": "DOMContentLoaded",
    "explain": "HTML სრულად დატვირთული და გაანალიზებულია."
  },
  {
    "word": "ჩატვირთვა ღონისძიება",
    "explain": "გვერდი სრულად დატვირთულია, რესურსების ჩათვლით."
  },
  {
    "word": "მოვლენის განტვირთვა",
    "explain": "გვერდი იტვირთება."
  },
  {
    "word": "მოვლენის ზომის შეცვლა",
    "explain": "ფანჯრის ზომის შეცვლა."
  },
  {
    "word": "მოვლენის გადახვევა",
    "explain": "გვერდის გადახვევა."
  },
  {
    "word": "ფოკუსირების ღონისძიება",
    "explain": "ელემენტი იძენს ყურადღებას."
  },
  {
    "word": "Blur Event",
    "explain": "ელემენტი კარგავს ყურადღებას."
  },
  {
    "word": "მოვლენის გაგზავნა",
    "explain": "ფორმის წარდგენა."
  },
  {
    "word": "მოვლენის შეცვლა",
    "explain": "შეყვანის მნიშვნელობა იცვლება."
  },
  {
    "word": "შეყვანის ღონისძიება",
    "explain": "შეყვანის ცვლილებები."
  },
  {
    "word": "დააწკაპუნეთ ღონისძიებაზე",
    "explain": "დაწკაპუნება ელემენტზე."
  },
  {
    "word": "DoubleClick Event",
    "explain": "ორმაგი დაწკაპუნებით ელემენტი."
  },
  {
    "word": "მაუსის მოვლენები",
    "explain": "დაკავშირებულია მაუსის მოქმედებებთან."
  },
  {
    "word": "კლავიატურის მოვლენები",
    "explain": "დაკავშირებულია კლავიატურის მოქმედებებთან."
  },
  {
    "word": "შეხება მოვლენებს",
    "explain": "დაკავშირებულია შეხების მოქმედებებთან."
  },
  {
    "word": "გადაათრიეთ მოვლენები",
    "explain": "დაკავშირებულია გადატანის მოქმედებებთან."
  },
  {
    "word": "API",
    "explain": "აპლიკაციის პროგრამირების ინტერფეისი."
  },
  {
    "word": "REST API",
    "explain": "Representational State Transfer API."
  },
  {
    "word": "GraphQL",
    "explain": "API-ების შეკითხვის ენა."
  },
  {
    "word": "API-ს მიღება",
    "explain": "HTTP მოთხოვნების განხორციელების მშობლიური გზა."
  },
  {
    "სიტყვა": "აქსიოსი",
    "explain": "HTTP კლიენტის ბიბლიოთეკა."
  },
  {
    "სიტყვა": "CORS",
    "explain": "Cross-Origin Resource Sharing."
  },
  {
    "word": "XML",
    "explain": "გაფართოებადი მარკირების ენა."
  },
  {
    "სიტყვა": "JWT",
    "explain": "JSON Web Token."
  },
  {
    "word": "OAuth",
    "explain": "ღია სტანდარტი წვდომის დელეგაციისთვის."
  },
  {
    "word": "ESLint",
    "explain": "Code linting tool."
  },
  {
    "სიტყვა": "ულამაზესი",
    "explain": "კოდის ფორმატირების ინსტრუმენტი."
  },
  {
    "სიტყვა": "გიტი",
    "explain": "ვერსიის კონტროლის სისტემა."
  },
  {
    "word": "GitHub",
    "explain": "Git საცავის ჰოსტინგი."
  },
  {
    "word": "Bitbucket",
    "explain": "Git საცავის ჰოსტინგი."
  },
  {
    "word": "GitLab",
    "explain": "Git საცავის ჰოსტინგი."
  },
  {
    "word": "CI/CD",
    "explain": "უწყვეტი ინტეგრაცია/უწყვეტი განლაგება."
  },
  {
    "სიტყვა": "ხუმრობა",
    "explain": "ტესტირების ჩარჩო."
  },
  {
    "სიტყვა": "მოკა",
    "explain": "ტესტირების ჩარჩო."
  },
  {
    "სიტყვა": "ჩაი",
    "explain": "Assertion ბიბლიოთეკა."
  },
  {
    "სიტყვა": "ფერმენტი",
    "explain": "Testing utility for React."
  },
  {
    "word": "React Testing Library",
    "explain": "ბიბლიოთეკის ტესტირება React კომპონენტებისთვის."
  },
  {
    "სიტყვა": "რედუქსი",
    "explain": "სახელმწიფო მართვის ბიბლიოთეკა."
  },
  {
    "word": "კონტექსტური API",
    "განმარტეთ": "რეაგირებს სახელმწიფო მენეჯმენტი."
  },
  {
    "word": "React Router",
    "explain": "React ბიბლიოთეკის მარშრუტიზაცია."
  },
  {
    "სიტყვა": "Vue",
    "explain": "პროგრესული JavaScript ჩარჩო."
  },
  {
    "სიტყვა": "კუთხოვანი",
    "explain": "ვებ აპლიკაციის ჩარჩო."
  },
  {
    "სიტყვა": "სველტი",
    "explain": "შემდგენელზე დაფუძნებული ჩარჩო."
  },
  {
    "word": "Next.js",
    "explain": "React Framework სერვერის მხრიდან რენდერისთვის."
  },
  {
    "სიტყვა": "გეტსბი",
    "explain": "სტატიკური საიტის გენერატორი React-ისთვის."
  },
  {
    "სიტყვა": "აპოლონი",
    "explain": "GraphQL განხორციელება."
  },
  {
    "სიტყვა": "ექსპრესი",
    "explain": "ვებ აპლიკაციის ჩარჩო Node.js-ისთვის."
  },
  {
    "სიტყვა": "კოა",
    "explain": "Web Framework for Node.js."
  },
  {
    "სიტყვა": "დაამაგრე",
    "explain": "Fast web frame for Node.js."
  },
  {
    "word": "Socket.io",
    "explain": "რეალურ დროში ორმხრივი მოვლენებზე დაფუძნებული კომუნიკაცია."
  },
  {
    "სიტყვა": "PM2",
    "explain": "პროცესის მენეჯერი Node.js-ისთვის."
  },
  {
    "word": "Package.json",
    "explain": "პროექტის მეტამონაცემების ფაილი."
  },
  {
    "word": "Node_modules",
    "explain": "საქაღალდე NPM პაკეტებისთვის."
  },
  {
    "word": "სერვერის მხრიდან რენდერი",
    "explain": "გვერდების რენდერი სერვერზე."
  },
  {
    "word": "კლიენტის მხრიდან რენდერი",
    "explain": "რენდერი ბრაუზერში."
  },
  {
    "word": "სტატიკური საიტის გენერაცია",
    "explain": "HTML-ის გენერირება აშენების დროს."
  },
  {
    "word": "დინამიური რენდერი",
    "explain": "სერვერის მხარის რენდერი ბოტებისთვის."
  },
  {
    "word": "პროგრესული ვებ აპლიკაცია",
    "explain": "ვებ აპლიკაცია მშობლიურის მსგავსი შესაძლებლობებით."
  },
  {
    "word": "მომსახურების თანამშრომელი",
    "explain": "სკრიპტი, რომელიც მუშაობს ფონზე."
  },
  {
    "word": "ვებ მანიფესტი",
    "explain": "განსაზღვრავს ვებ აპლიკაციას."
  },
  {
    "word": "საპასუხო დიზაინი",
    "explain": "დიზაინი, რომელიც მუშაობს ნებისმიერ მოწყობილობაზე."
  },
  {
    "word": "Flexbox",
    "explain": "განლაგების მოდელი CSS-ში."
  },
  {
    "სიტყვა": "ბადე",
    "explain": "CSS ბადის განლაგების სისტემა."
  },
  {
    "word": "მედია მოთხოვნები",
    "explain": "CSS ტექნიკა რეაგირებისთვის."
  },
  {
    "word": "Bootstrap",
    "explain": "Front-end frame."
  },
  {
    "word": "Tailwind CSS",
    "explain": "Utility-first CSS Framework."
  },
  {
    "სიტყვა": "სასი",
    "explain": "CSS წინასწარი პროცესორი."
  },
  {
    "სიტყვა": "ნაკლები",
    "explain": "CSS წინასწარი პროცესორი."
  },
  {
    "word": "PostCSS",
    "explain": "CSS ტრანსფორმაციის ინსტრუმენტი."
  },
  {
    "word": "ავტოფიქსატორი",
    "explain": "PostCSS დანამატი გამყიდველის პრეფიქსებისთვის."
  },
  {
    "word": "CSS მოდულები",
    "explain": "ადგილობრივი ფარგლების CSS."
  },
  {
    "word": "სტილირებული კომპონენტები",
    "explain": "CSS JS ბიბლიოთეკაში."
  },
  {
    "სიტყვა": "JSS",
    "explain": "CSS JS ბიბლიოთეკაში."
  },
  {
    "სიტყვა": "ემოცია",
    "explain": "CSS JS ბიბლიოთეკაში."
  },
  {
    "word": "Material-UI",
    "explain": "React კომპონენტების ბიბლიოთეკა."
  },
  {
    "სიტყვა": "ჭიანჭველების დიზაინი",
    "explain": "React-ის დიზაინის ბიბლიოთეკა."
  },
  {
    "word": "სემანტიკური ინტერფეისი",
    "explain": "UI კომპონენტის ჩარჩო."
  },
  {
    "word": "MDBootstrap",
    "explain": "Material Design for Bootstrap."
  },
  {
    "სიტყვა": "ფიგურა",
    "explain": "დიზაინის ინსტრუმენტი."
  },
  {
    "სიტყვა": "ესკიზი",
    "explain": "დიზაინის ინსტრუმენტი."
  },
  {
    "word": "Adobe XD",
    "explain": "დიზაინის ინსტრუმენტი."
  },
  {
    "word": "InVision",
    "explain": "ციფრული პროდუქტის დიზაინის პლატფორმა."
  },
  {
    "სიტყვა": "ზეპლინი",
    "explain": "თანამშრომლობის ინსტრუმენტი დიზაინერებისა და დეველოპერებისთვის."
  },
  {
    "სიტყვა": "დოკერი",
    "explain": "პლატფორმა აპლიკაციების შემუშავების, გადაზიდვისა და გაშვებისთვის."
  },
  {
    "სიტყვა": "კუბერნეტები",
    "explain": "კონტეინერის ორკესტრირების სისტემა."
  },
  {
    "სიტყვა": "მაწანწალა",
    "explain": "ვირტუალური მანქანების გარემოს შექმნისა და მართვის ინსტრუმენტი."
  },
  {
    "სიტყვა": "ანსიბილი",
    "explain": "ავტომატური პლატფორმა IT ამოცანებისთვის."
  },
  {
    "სიტყვა": "ტერაფორმი",
    "explain": "ინფრასტრუქტურა, როგორც კოდის პროგრამული ინსტრუმენტი."
  },
  {
    "სიტყვა": "AWS",
    "explain": "Amazon Web Services, Cloud Computing Services."
  },
  {
    "სიტყვა": "ლურჯი",
    "explain": "Microsoft-ის ღრუბლოვანი გამოთვლითი სერვისი."
  },
  {
    "word": "Google Cloud",
    "explain": "Google-ის ღრუბლოვანი გამოთვლითი სერვისი."
  },
  {
    "word": "DigitalOcean",
    "explain": "Cloud ინფრასტრუქტურის პროვაიდერი."
  },
  {
    "სიტყვა": "ჰეროკუ",
    "explain": "აპლიკაციების განლაგების ღრუბლოვანი პლატფორმა."
  },
  {
    "word": "Netlify",
    "explain": "ჰოსტინგი და სარეზერვო სერვისები ვებ აპლიკაციებისთვის."
  },
  {
    "სიტყვა": "ვერსელი",
    "explain": "პლატფორმა ფრონტენდის ჩარჩოებისა და სტატიკური საიტებისთვის."
  },
  {
    "word": "Firebase",
    "explain": "პლატფორმა მობილური და ვებ აპლიკაციების შესაქმნელად."
  },
  {
    "სიტყვა": "MongoDB",
    "explain": "NoSQL მონაცემთა ბაზა."
  },
  {
    "word": "PostgreSQL",
    "explain": "ობიექტურ-რელაციური მონაცემთა ბაზა."
  },
  {
    "word": "MySQL",
    "explain": "რელატიური მონაცემთა ბაზა."
  },
  {
    "word": "SQLite",
    "explain": "SQL-ის თვითმყოფადი მონაცემთა ბაზა."
  },
  {
    "სიტყვა": "რედისი",
    "explain": "მეხსიერების მონაცემთა სტრუქტურის შენახვა."
  },
  {
    "word": "Elasticsearch",
    "explain": "საძიებო და ანალიტიკური სისტემა."
  },
  {
    "სიტყვა": "დასვენება",
    "explain": "არქიტექტურული სტილი API-ებისთვის."
  },
  {
    "სიტყვა": "საპონი",
    "explain": "პროტოკოლი ვებ სერვისებისთვის."
  },
  {
    "სიტყვა": "gRPC",
    "explain": "მაღალი ეფექტურობის RPC ჩარჩო."
  },
  {
    "word": "ვებსოკეტები",
    "explain": "ინტერაქტიული კომუნიკაციის პროტოკოლი."
  },
  {
    "word": "უსერვერსო",
    "explain": "კოდის გაშვება სერვერების მართვის გარეშე."
  },
  {
    "word": "მიკროსერვისები",
    "explain": "არქიტექტურული სტილი შენობის აპლიკაციებისთვის."
  },
  {
    "სიტყვა": "მონოლითური",
    "explain": "ერთსაფეხურიანი პროგრამული აპლიკაცია."
  },
  {
    "word": "DevOps",
    "explain": "პროგრამული უზრუნველყოფის შემუშავებისა და ოპერაციების პრაქტიკა."
  },
  {
    "სიტყვა": "სწრაფი",
    "explain": "განმეორებითი მიდგომა პროექტის მენეჯმენტში."
  },
  {
    "სიტყვა": "სკრამი",
    "explain": "Framework for Agile Development."
  },
  {
    "სიტყვა": "კანბანი",
    "განმარტეთ": "საქმის მართვის მეთოდოლოგია"
  },
  {
    "სიტყვა": "ჩანჩქერი",
    "explain": "პროექტის მენეჯმენტის თანმიმდევრული მოდელი."
  },
  {
    "სიტყვა": "MVP",
    "explain": "მინიმალური სიცოცხლისუნარიანი პროდუქტი."
  },
  {
    "სიტყვა": "POC",
    "explain": "კონცეფციის დამადასტურებელი"
  },
  {
    "სიტყვა": "UX",
    "explain": "მომხმარებლის გამოცდილება."
  },
  {
    "word": "UI",
    "explain": "მომხმარებლის ინტერფეისი."
  },
  {
    "word": "A/B ტესტირება",
    "explain": "შედარებითი ტესტირების მეთოდი."
  },
  {
    "word": "ანალიტიკა",
    "explain": "მონაცემთა ანალიზი ინფორმაციისთვის."
  },
  {
    "სიტყვა": "SEO",
    "explain": "Search Engine Optimization."
  },
  {
    "სიტყვა": "SEM",
    "explain": "Search Engine Marketing."
  },
  {
    "სიტყვა": "PPC",
    "explain": "Pay-per-Click რეკლამა."
  },
  {
    "word": "კონვერტაციის კურსი",
    "explain": "მომხმარებელთა პროცენტი, რომლებიც იღებენ სასურველ ქმედებებს."
  },
  {
    "სიტყვა": "KPI",
    "explain": "Key Performance Indicator."
  },
  {
    "სიტყვა": "ROI",
    "განმარტეთ": "ინვესტიციის დაბრუნება"
  },
  {
    "სიტყვა": "CTA",
    "explain": "Call to Action."
  },
  {
    "სიტყვა": "წამყვანი თაობა",
    "განმარტეთ": "პერსპექტივების მოზიდვის პროცესი"
  },
  {
    "word": "მომხმარებლის შეძენა",
    "explain": "ახალი მომხმარებლების მოპოვების პროცესი."
  },
  {
    "word": "Churn Rate",
    "explain": "შეფასება, რომლითაც კლიენტები წყვეტენ ბიზნესის კეთებას."
  },
  {
    "სიტყვა": "შეკავება",
    "explain": "მომხმარებლის შენარჩუნების უნარი."
  },
  {
    "სიტყვა": "LTV",
    "explain": "მომხმარებლის სიცოცხლის ღირებულება."
  },
  {
    "სიტყვა": "CAC",
    "explain": "მომხმარებლის შეძენის ღირებულება."
  },
  {
    "word": "ბაზრის სეგმენტაცია",
    "განმარტეთ": "ბაზრის ჯგუფებად დაყოფა."
  },
  {
    "სიტყვა": "სამიზნე ბაზარი",
    "explain": "პოტენციური კლიენტების კონკრეტული ჯგუფი."
  },
  {
    "word": "ბრენდის ცნობადობა",
    "explain": "რა ხარისხით არის აღიარებული ბრენდი."
  },
  {
    "სიტყვა": "პოზიციონირება",
    "explain": "ბრენდის დამკვიდრება მომხმარებელთა გონებაში."
  },
  {
    "word": "Benchmarking",
    "explain": "შედარება ინდუსტრიის სტანდარტებთან."
  },
  {
    "word": "SWOT ანალიზი",
    "განმარტეთ": "ძლიერი, სუსტი მხარეები, შესაძლებლობები, საფრთხეების ანალიზი."
  },
  {
    "word": "კონკურენტის ანალიზი",
    "explain": "კონკურენტების სტრატეგიების შეფასება."
  },
  {
    "word": "კონტენტ მარკეტინგი",
    "explain": "კონტენტის შექმნა და გავრცელება."
  },
  {
    "word": "შემავალი მარკეტინგი",
    "explain": "მოზიდვა მომხმარებელთა კონტენტის მეშვეობით."
  },
  {
    "word": "გამავალი მარკეტინგი",
    "explain": "ტრადიციული მარკეტინგის მეთოდები."
  },
  {
    "word": "შვილობილი მარკეტინგი",
    "explain": "საკომისიოს შოვნა პროდუქციის რეკლამით."
  },
  {
    "word": "Influencer Marketing",
    "explain": "ინფლუენსერების გამოყენება პროდუქტების მარკეტინგისთვის."
  },
  {
    "word": "ელ.ფოსტის მარკეტინგი",
    "explain": "მარკეტინგის შეტყობინებების გაგზავნა ელექტრონული ფოსტით."
  },
  {
    "word": "სოციალური მედიის მარკეტინგი",
    "explain": "სოციალური მედიის პლატფორმების გამოყენება მარკეტინგისთვის."
  },
  {
    "word": "საზოგადოებასთან ურთიერთობა",
    "explain": "ინფორმაციის გავრცელების მართვა."
  },
  {
    "word": "კრიზისის მართვა",
    "explain": "ორგანიზაციისთვის საფრთხის მართვა."
  },
  {
    "word": "რეპუტაციის მენეჯმენტი",
    "განმარტეთ": "ორგანიზაციის აღქმაზე ზეგავლენა"
  },
  {
    "word": "ღონისძიების მარკეტინგი",
    "explain": "პროდუქტების პოპულარიზაცია ღონისძიებების საშუალებით."
  },
  {
    "word": "პროდუქტის გაშვება",
    "explain": "ახალი პროდუქტის შემოტანა ბაზარზე"
  },
  {
    "სიტყვა": "ბრენდინგი",
    "explain": "პროდუქტის/კომპანიის განსხვავებული იმიჯის შექმნა."
  },
  {
    "word": "ფასების სტრატეგია",
    "explain": "პროდუქტის ფასის განსაზღვრა."
  },
  {
    "word": "გაყიდვების სტრატეგია",
    "explain": "დაგეგმე პროდუქციის/მომსახურების გაყიდვა."
  },
  {
    "სიტყვა": "ტყვიის აღზრდა",
    "განმარტეთ": "მყიდველებთან ურთიერთობის განვითარება"
  },
  {
    "word": "გაყიდვების ძაბრი",
    "explain": "მომხმარებლის მოგზაურობა შესაძენად."
  },
  {
    "სიტყვა": "CRM",
    "explain": "Customer Relationship Management."
  },
  {
    "word": "ბაზრის კვლევა",
    "განმარტეთ": "მომხმარებელთა საჭიროებების შესახებ ინფორმაციის შეგროვება"
  },
  {
    "word": "მონაცემთა ანალიზი",
    "explain": "მონაცემების გამოკვლევა, გაწმენდა, ტრანსფორმაცია და მოდელირება."
  },
  {
    "word": "მანქანის სწავლება",
    "explain": "ალგორითმები, რომლებიც ავტომატურად უმჯობესდება გამოცდილებით."
  },
  {
    "სიტყვა": "ხელოვნური ინტელექტი",
    "განმარტეთ": "ადამიანის ინტელექტის სიმულაცია მანქანებში."
  },
  {
    "word": "მონაცემთა მოპოვება",
    "explain": "თარგების აღმოჩენის პროცესი მონაცემთა დიდ ნაკრებებში."
  },
  {
    "სიტყვა": "დიდი მონაცემები",
    "explain": "დიდი, რთული მონაცემთა ნაკრები."
  },
  {
    "word": "Cloud Computing",
    "explain": "დისტანციური სერვერების გამოყენება მონაცემთა შენახვის, მართვისა და დამუშავებისთვის."
  },
  {
    "word": "ვირტუალური რეალობა",
    "explain": "იმიტირებული გამოცდილება კომპიუტერული ტექნოლოგიების გამოყენებით."
  },
  {
    "word": "გაფართოებული რეალობა",
    "explain": "რეალური სამყაროს გარემოს გაძლიერება კომპიუტერის მიერ გენერირებული აღქმის ინფორმაციით."
  },
  {
    "word": "ბლოკჩეინი",
    "explain": "დეცენტრალიზებული, განაწილებული ledger ტექნოლოგია."
  },
  {
    "word": "კრიპტოვალუტა",
    "explain": "ციფრული ან ვირტუალური ვალუტა უსაფრთხოებისთვის კრიპტოგრაფიის გამოყენებით."
  },
  {
    "სიტყვა": "ბიტკოინი",
    "explain": "ციფრული ვალუტის ტიპი."
  },
  {
    "სიტყვა": "ეთერიუმი",
    "explain": "ბლოკჩეინზე დაფუძნებული პროგრამული პლატფორმა."
  },
  {
    "word": "ჭკვიანი კონტრაქტი",
    "explain": "თვითშემსრულებელი ხელშეკრულება პირობებით პირდაპირ კოდში ჩაწერილი."
  },
  {
    "სიტყვა": "IoT",
    "explain": "ინტერნეტი ნივთები; გამოთვლითი მოწყობილობების ურთიერთდაკავშირება ყოველდღიურ ობიექტებში."
  },
  {
    "word": "კიბერუსაფრთხოება",
    "explain": "სისტემების, ქსელების და პროგრამების დაცვა ციფრული შეტევებისგან."
  },
  {
    "word": "მავნე პროგრამა",
    "explain": "მავნე პროგრამა, რომელიც განკუთვნილია კომპიუტერების დაზიანების ან გამორთვისთვის."
  },
  {
    "word": "ფიშინგი",
    "explain": "სენსიტიური ინფორმაციის მოპოვების თაღლითური მცდელობა."
  },
  {
    "word": "დაშიფვრა",
    "explain": "ინფორმაციის ან მონაცემების კოდად გადაქცევა არაავტორიზებული წვდომის თავიდან ასაცილებლად."
  },
  {
    "word": "Firewall",
    "explain": "ქსელის უსაფრთხოების სისტემა, რომელიც აკონტროლებს და აკონტროლებს შემომავალ და გამავალ ქსელის ტრაფიკს."
  },
  {
    "სიტყვა": "VPN",
    "explain": "ვირტუალური პირადი ქსელი; აფართოებს კერძო ქსელს საჯარო ქსელში."
  },
  {
    "word": "მონაცემთა დარღვევა",
    "explain": "უსაფრთხოების ინციდენტი, რომლის დროსაც ინფორმაციაზე წვდომა ხდება ავტორიზაციის გარეშე."
  },
  {
    "word": "DDoS შეტევა",
    "explain": "მომსახურების განაწილებული უარყოფა; არღვევს მიზნობრივი სერვერის, სერვისის ან ქსელის ნორმალურ ტრაფიკს."
  },
  {
    "word": "Ransomware",
    "explain": "მავნე პროგრამის ტიპი, რომელიც ემუქრება მსხვერპლის მონაცემების გამოქვეყნებას ან სამუდამოდ დაბლოკავს მასზე წვდომას, თუ გამოსასყიდის გადახდა არ მოხდება."
  },
  {
    "word": "შეღწევადობის ტესტირება",
    "explain": "ავტორიზებული სიმულირებული კიბერშეტევა კომპიუტერულ სისტემაზე უსაფრთხოების შესაფასებლად."
  },
  {
    "word": "ინციდენტის რეაგირება",
    "explain": "უსაფრთხოების დარღვევის შედეგების დამუშავებისა და მართვის მიდგომა."
  },
  {
    "word": "რისკის შეფასება",
    "განმარტეთ": "რისკების გამოვლენისა და შეფასების პროცესი."
  },
  {
    "სიტყვა": "შეთანხმება",
    "explain": "შეესაბამება კანონებს, რეგულაციებს, სტანდარტებს და ეთიკურ პრაქტიკას."
  },
  {
    "სიტყვა": "GDPR",
    "explain": "მონაცემთა დაცვის ზოგადი რეგულაცია; ევროკავშირის კანონი მონაცემთა დაცვისა და კონფიდენციალურობის შესახებ."
  },
  {
    "word": "ISO სტანდარტები",
    "explain": "საერთაშორისო სტანდარტები პროდუქტების, სერვისებისა და სისტემებისთვის."
  },
  {
    "word": "ხარისხის უზრუნველყოფა",
    "explain": "პროდუქტის ან მომსახურების ხარისხის უზრუნველყოფა."
  },
  {
    "სიტყვა": "ექვს სიგმა",
    "explain": "პროცესის გაუმჯობესების ტექნიკის ნაკრები."
  },
  {
    "word": "Lean Manufacturing",
    "explain": "ნარჩენების მინიმიზაციის სისტემატური მეთოდი."
  },
  {
    "word": "მომარაგების ჯაჭვის მენეჯმენტი",
    "განმარტეთ": "საქონლისა და მომსახურების ნაკადის მართვა"
  },
  {
    "სიტყვა": "ლოგისტიკა",
    "explain": "კომპლექსური ოპერაციების დეტალური კოორდინაცია."
  },
  {
    "word": "ინვენტარის მართვა",
    "explain": "არაკაპიტალიზებული აქტივების და საფონდო ნივთების ზედამხედველობა."
  },
  {
    "word": "შესყიდვა",
    "explain": "საქონლის, მომსახურების ან სამუშაოს შეძენის პროცესი."
  },
  {
    "სიტყვა": "წარმოება",
    "განმარტეთ": "საქონლის წარმოება შრომის, მანქანების, ხელსაწყოების და ქიმიური ან ბიოლოგიური დამუშავების გამოყენებით."
  },
  {
    "სიტყვა": "წარმოება",
    "განმარტეთ": "საქონლისა და მომსახურების შექმნის პროცესი."
  },
  {
    "word": "ოპერაციების მენეჯმენტი",
    "explain": "წარმოების პროცესების ზედამხედველობა, დიზაინი და კონტროლი."
  },
  {
    "word": "პროექტის მენეჯმენტი",
    "explain": "სამუშაოს დაგეგმვა, წამოწყება, შესრულება, კონტროლი და დახურვა."
  },
  {
    "word": "რესურსების მართვა",
    "explain": "ორგანიზაციის რესურსების ეფექტური და ეფექტური გამოყენება."
  },
  {
    "word": "დაინტერესებული მხარეების მენეჯმენტი",
    "განმარტეთ": "ურთიერთობების მართვა ადამიანებთან, რომლებსაც აქვთ ინტერესი პროექტით."
  },
  {
    "word": "Scope Management",
    "explain": "პროცესი განსაზღვრის რა სამუშაოა საჭირო."
  },
  {
    "word": "განრიგის მენეჯმენტი",
    "explain": "პროექტის ვადების დაგეგმვა, შესრულება და მონიტორინგი."
  },
  {
    "word": "ღირებულების მართვა",
    "განმარტეთ": "ბიუჯეტის დაგეგმვა და კონტროლი"
  },
  {
    "word": "ხარისხის მენეჯმენტი",
    "explain": "დარწმუნება, რომ პროექტი აკმაყოფილებს განსაზღვრულ ხარისხის სტანდარტებს."
  },
  {
    "word": "რისკების მართვა",
    "explain": "საფრთხეების იდენტიფიცირების, შეფასების და კონტროლის პროცესი."
  },
  {
    "word": "საკითხთა მენეჯმენტი",
    "explain": "პროექტის შესრულების დროს წარმოქმნილ პრობლემებთან გამკლავება."
  },
  {
    "word": "Change Management",
    "explain": "მიდგომა გარდამავალი პირების, გუნდებისა და ორგანიზაციებისადმი."
  },
  {
    "word": "კომუნიკაციის მენეჯმენტი",
    "explain": "პროექტის ინფორმაციის დროული და სათანადო დაგეგმვა, შეგროვება, შექმნა, განაწილება, შენახვა, მოძიება, მართვა, კონტროლი, მონიტორინგი და საბოლოო განთავსება."
  },
  {
    "word": "შესყიდვების მენეჯმენტი",
    "explain": "პროცესები პროდუქტების, სერვისების ან შედეგების შესაძენად ან შესაძენად, რომელიც საჭიროა პროექტის გუნდის გარეთ."
  },
  {
    "word": "ინტეგრაციის მენეჯმენტი",
    "explain": "პროექტის ელემენტების კოორდინაცია."
  },
  {
    "word": "დაინტერესებულ მხარეთა ჩართულობა",
    "განმარტეთ": "დაინტერესებულ მხარეებთან ჩართვის ქმედებების სისტემატური იდენტიფიკაცია, ანალიზი, დაგეგმვა და განხორციელება."
  },
  {
    "word": "ადამიანური რესურსების მართვა",
    "explain": "თანამშრომლების მუშაობის მაქსიმალურად გაზრდა."
  },
  {
    "word": "შესრულების მენეჯმენტი",
    "განმარტეთ": "სამუშაო გარემოს შექმნის პროცესი, რომელშიც ადამიანებს შეუძლიათ შეასრულონ თავიანთი შესაძლებლობების მაქსიმუმი."
  },
  {
    "სიტყვა": "კარიერის განვითარება",
    "განმარტეთ": "სწავლის, მუშაობის, დასვენებისა და გადასვლების მართვის მთელი ცხოვრების პროცესი."
  },
  {
    "word": "ტრენინგი და განვითარება",
    "განმარტეთ": "საგანმანათლებლო საქმიანობა კომპანიაში"
  },
  {
    "სიტყვა": "ორგანიზაციული განვითარება",
    "განმარტეთ": "წარმატებული ორგანიზაციული ცვლილებებისა და შესრულების შესწავლა"
  },
  {
    "word": "თანამშრომლებთან ურთიერთობა",
    "განმარტეთ": "კომპანიის ძალისხმევა, მართოს ურთიერთობა დამსაქმებელსა და თანამშრომლებს შორის."
  },
  {
    "word": "ნიჭიერის მენეჯმენტი",
    "განმარტეთ": "ორგანიზაციისთვის საჭირო ადამიანური კაპიტალის მოლოდინი"
  },
  {
    "სიტყვა": "დასაქმება",
    "explain": "შესაფერისი კანდიდატების მოზიდვის, შერჩევისა და დანიშვნის პროცესი."
  },
  {
    "word": "თანამშრომლების ჩართულობა",
    "განმარტეთ": "რაოდენობით თანამშრომლები ვნებიანად გრძნობენ თავიანთ სამუშაოს."
  },
  {
    "სიტყვა": "კომპენსაცია და სარგებელი",
    "განმარტეთ": "თანამშრომლებისთვის მიცემული ჯამური ჯილდოები."
  },
  {
    "სიტყვა": "შრომის სამართალი",
    "განმარტეთ": "შრომითი ურთიერთობების შესახებ კანონთა ორგანო"
  },
  {
    "word": "სამუშაო ძალის დაგეგმვა",
    "განმარტეთ": "ორგანიზაციის მომავალი სამუშაო ძალის საჭიროებების ანალიზის პროცესი."
  },
  {
    "word": "მემკვიდრეობის დაგეგმვა",
    "განმარტეთ": "შიდა პერსონალის იდენტიფიცირებისა და განვითარების პროცესი."
  },
  {
    "სიტყვა": "მრავალფეროვნება და ინკლუზია",
    "განმარტეთ": "სხვადასხვა ჯგუფების წარმომადგენლობისა და მონაწილეობის ხელშემწყობი პოლიტიკა და პროგრამები."
  },
  {
    "სიტყვა": "თანამშრომლების კეთილდღეობა",
    "განმარტეთ": "პროგრამები ჯანმრთელობისა და კეთილდღეობის ხელშეწყობისთვის სამუშაო ადგილზე."
  },
  {
    "სიტყვა": "სამრეწველო ურთიერთობები",
    "განმარტეთ": "ურთიერთობა მენეჯმენტსა და მუშაკებს შორის."
  },
  {
    "სიტყვა": "ორგანიზაციული კულტურა",
    "განმარტეთ": "ღირებულებები და ქცევები, რომლებიც ხელს უწყობენ ორგანიზაციის უნიკალურ სოციალურ და ფსიქოლოგიურ გარემოს."
  },
  {
    "სიტყვა": "ორგანიზაციული სტრუქტურა",
    "explain": "სისტემა, რომელიც გამოიყენება ორგანიზაციაში იერარქიის დასადგენად."
  },
  {
    "სიტყვა": "ხელმძღვანელობა",
    "განმარტეთ": "ადამიანებზე ხელმძღვანელობის, ხელმძღვანელობის ან გავლენის მოხდენის უნარი."
  },
  {
    "სიტყვა": "მენეჯმენტი",
    "explain": "ობიექტებთან ან ადამიანებთან ურთიერთობის ან კონტროლის პროცესი."
  },
  {
    "word": "სტრატეგიული დაგეგმვა",
    "explain": "ორგანიზაციის სტრატეგიის განსაზღვრის პროცესი."
  },
  {
    "word": "ბიზნეს სტრატეგია",
    "განმარტეთ": "გეგმა ბიზნესის წარმატებული საქმიანობისთვის"
  },
  {
    "word": "ოპერაციული სტრატეგია",
    "განმარტეთ": "საქმიანი პროცესების დაგეგმვა"
  },
  {
    "word": "PEST ანალიზი",
    "explain": "ინსტრუმენტი, რომელიც გამოიყენება მაკროგარემოს ფაქტორების გასაანალიზებლად."
  },
  {
    "word": "ბაზრის ანალიზი",
    "განმარტეთ": "ბაზრის პირობების კვლევა"
  },
  {
    "word": "კონკურენტული ანალიზი",
    "explain": "სტრატეგია ძირითადი კონკურენტების იდენტიფიცირების მიზნით."
  },
  {
    "word": "ბიზნეს მოდელი",
    "განმარტეთ": "გეგმა ბიზნესის წარმატებული საქმიანობისთვის"
  },
  {
    "სიტყვა": "ბიზნეს გეგმა",
    "explain": "წერილობითი დოკუმენტი, რომელიც აღწერს ბიზნესის ბუნებას."
  },
  {
    "word": "მარკეტინგის გეგმა",
    "explain": "ბიზნეს დოკუმენტი, რომელიც ასახავს მარკეტინგულ სტრატეგიას."
  },
  {
    "სიტყვა": "ფინანსური დაგეგმვა",
    "explain": "საჭიროა კაპიტალის შეფასების პროცესი."
  },
  {
    "სიტყვა": "ბიუჯეტი",
    "განმარტეთ": "ფულის დახარჯვის გეგმის შექმნის პროცესი"
  },
  {
    "word": "პროგნოზირება",
    "განმარტეთ": "მომავლის პროგნოზების გაკეთების პროცესი"
  },
  {
    "word": "ბუღალტერია",
    "განმარტეთ": "ფინანსური ინფორმაციის გაზომვა, დამუშავება და გადაცემა."
  },
  {
    "word": "აუდიტი",
    "განმარტეთ": "ფინანსური ჩანაწერების შემოწმება"
  },
  {
    "სიტყვა": "გადასახადები",
    "განმარტეთ": "მთავრობის მიერ დაწესებული გადასახადი"
  },
  {
    "word": "ფინანსური ანგარიშგება",
    "explain": "ფინანსური შედეგების გამჟღავნება."
  },
  {
    "სიტყვა": "ინვესტიცია",
    "explain": "აქტივი ან ნივთი შეძენილი შემოსავლის გამომუშავების მიზნით."
  },
  {
    "სიტყვა": "საფონდო ბაზარი",
    "განმარტეთ": "საქონლის მყიდველთა და გამყიდველთა აგრეგატი"
  },
  {
    "word": "საბანკო საქმე",
    "განმარტეთ": "ინდუსტრი, რომელიც ეხება ნაღდ ფულს, კრედიტს და სხვა ფინანსურ ოპერაციებს."
  },
  {
    "სიტყვა": "დაზღვევა",
    "განმარტეთ": "ფინანსური ზარალისგან დაცვის საშუალებები"
  },
  {
    "word": "უძრავი ქონება",
    "განმარტეთ": "საკუთრება, რომელიც შედგება მიწისა და შენობებისაგან."
  },
  {
    "word": "ელექტრონული კომერცია",
    "explain": "საქონლის ან მომსახურების ყიდვა ან გაყიდვა ინტერნეტის გამოყენებით."
  },
  {
    "word": "ცალობით",
    "განმარტეთ": "სამომხმარებლო საქონლის ან მომსახურების გაყიდვის პროცესი."
  },
  {
    "word": "მომარაგების ჯაჭვი",
    "განმარტეთ": "ორგანიზაციების, ადამიანების, აქტივობების, ინფორმაციისა და რესურსების სისტემა, რომლებიც მონაწილეობენ პროდუქტის ან სერვისის გადატანაში."
  },
  {
    "word": "პროდუქტის მენეჯმენტი",
    "explain": "ორგანიზაციული ფუნქცია, რომელიც წარმართავს პროდუქტის სასიცოცხლო ციკლის ყველა საფეხურს."
  },
  {
    "word": "ხარისხის კონტროლი",
    "explain": "პროცესი ხარისხის გარკვეული დონის უზრუნველსაყოფად."
  },
  {
    "word": "ადამიანური რესურსები",
    "განმარტეთ": "განყოფილება, რომელიც პასუხისმგებელია პერსონალის მართვაზე."
  },
  {
    "სიტყვა": "გაყიდვები",
    "explain": "საქმიანობა, რომელიც დაკავშირებულია საქონლის ან მომსახურების გაყიდვასთან."
  },
  {
    "word": "მომხმარებელთა მომსახურება",
    "explain": "მომხმარებლებისთვის მომსახურების მიწოდება."
  },
  {
    "სიტყვა": "მარკეტინგი",
    "explain": "მომხმარებლებთან ურთიერთობის დამყარების ბიზნეს პროცესი."
  },
  {
    "word": "რეკლამა",
    "განმარტეთ": "რამეზე საზოგადოების ყურადღების მიქცევის აქცია"
  },
  {
    "word": "ციფრული მარკეტინგი",
    "explain": "პროდუქტების ან სერვისების მარკეტინგი ციფრული ტექნოლოგიების გამოყენებით."
  },
  {
    "word": "სოციალური მედია",
    "განმარტეთ": "ინტერაქტიული ტექნოლოგიები, რომლებიც ხელს უწყობენ ინფორმაციის შექმნას და გაზიარებას."
  },
  {
    "word": "შინაარსის შექმნა",
    "explain": "ინფორმაციის წვლილი ციფრულ მედიაში."
  },
  {
    "word": "მონაცემთა მეცნიერება",
    "განმარტეთ": "ინტერდისციპლინარული სფერო, რომელიც იყენებს მეცნიერულ მეთოდებს მონაცემებიდან ცოდნისა და შეხედულებების ამოსაღებად."
  },
  {
    "სიტყვა": "ღრმა სწავლა",
    "explain": "მანქანური სწავლების ნაწილი, რომელიც დაფუძნებულია ხელოვნურ ნერვულ ქსელებზე."
  },
  {
    "word": "Computer Vision",
    "explain": "კომპიუტერული მეცნიერების სფერო, რომელიც მუშაობს კომპიუტერებს სურათების დანახვის, ამოცნობისა და დამუშავების საშუალებას აძლევს."
  },
  {
    "word": "ბუნებრივი ენის დამუშავება",
    "explain": "ხელოვნური ინტელექტის ფილიალი, რომელიც ეხება კომპიუტერებსა და ადამიანის ენას შორის ურთიერთქმედებას."
  },
  {
    "სიტყვა": "რობოტიკა",
    "განმარტეთ": "ინჟინერიისა და მეცნიერების ინტერდისციპლინური ფილიალი, რომელიც მოიცავს რობოტების დიზაინს, მშენებლობას, ექსპლუატაციას და გამოყენებას."
  },
  {
    "word": "ჭკვიანი კონტრაქტები",
    "explain": "კომპიუტერული პროტოკოლები, რომლებიც განკუთვნილია კონტრაქტის მოლაპარაკების ციფრულად გასაადვილებლად, გადამოწმების ან აღსრულების მიზნით."
  },
  {
    "word": "თამაშის განვითარება",
    "explain": "ვიდეო თამაშის შემუშავების პროცესი."
  },
  {
    "word": "3D მოდელირება",
    "explain": "სპეციალიზებული პროგრამული უზრუნველყოფის საშუალებით ობიექტის ნებისმიერი ზედაპირის სამ განზომილებაში მათემატიკური წარმოდგენის შემუშავების პროცესი."
  }
]
